docopt/__init__.py
docopt/py.typed
docopt_ng-0.8.1.dist-info/LICENSE-MIT
docopt_ng-0.8.1.dist-info/METADATA
docopt_ng-0.8.1.dist-info/WHEEL
docopt_ng-0.8.1.dist-info/top_level.txt
docopt_ng-0.8.1.dist-info/RECORD
