Metadata-Version: 2.1
Name: docopt-ng
Version: 0.8.1
Summary: Jazzband-maintained fork of docopt, the humane command line arguments parser.
Home-page: https://github.com/jazzband/docopt-ng
Author: Nick Crews
Author-email: nicholas.b.crews@gmail.com
License: MIT
Classifier: Development Status :: 4 - Beta
Classifier: Intended Audience :: Developers
Classifier: License :: OSI Approved :: MIT License
Classifier: Operating System :: OS Independent
Classifier: Programming Language :: Python
Classifier: Programming Language :: Python :: 3
Classifier: Programming Language :: Python :: 3 :: Only
Classifier: Programming Language :: Python :: 3.7
Classifier: Programming Language :: Python :: 3.8
Classifier: Programming Language :: Python :: 3.9
Classifier: Programming Language :: Python :: 3.10
Classifier: Programming Language :: Python :: Implementation :: CPython
Classifier: Programming Language :: Python :: Implementation :: PyPy
Requires-Python: >=3.7
Provides-Extra: dev
License-File: LICENSE-MIT
